audio_degrader/AllDegradations.py
audio_degrader/AllDegradations.pyc
audio_degrader/AudioFile.py
audio_degrader/AudioFile.pyc
audio_degrader/BaseDegradation.py
audio_degrader/BaseDegradation.pyc
audio_degrader/DegradationConvolution.py
audio_degrader/DegradationConvolution.pyc
audio_degrader/DegradationDynamicRangeCompression.py
audio_degrader/DegradationDynamicRangeCompression.pyc
audio_degrader/DegradationEqualization.py
audio_degrader/DegradationEqualization.pyc
audio_degrader/DegradationGain.py
audio_degrader/DegradationGain.pyc
audio_degrader/DegradationMix.py
audio_degrader/DegradationMix.pyc
audio_degrader/DegradationMp3.py
audio_degrader/DegradationMp3.pyc
audio_degrader/DegradationNormalization.py
audio_degrader/DegradationNormalization.pyc
audio_degrader/DegradationPitchShifting.py
audio_degrader/DegradationPitchShifting.pyc
audio_degrader/DegradationResample.py
audio_degrader/DegradationResample.pyc
audio_degrader/DegradationSpeed.py
audio_degrader/DegradationSpeed.pyc
audio_degrader/DegradationTimeStretching.py
audio_degrader/DegradationTimeStretching.pyc
audio_degrader/DegradationTrim.py
audio_degrader/DegradationTrim.pyc
audio_degrader/ParametersParser.py
audio_degrader/ParametersParser.pyc
audio_degrader/__init__.py
audio_degrader/__init__.pyc
audio_degrader/utils.py
audio_degrader/utils.pyc
audio_degrader/__pycache__/AllDegradations.cpython-37.pyc
audio_degrader/__pycache__/AudioFile.cpython-37.pyc
audio_degrader/__pycache__/AudioFile.cpython-39.pyc
audio_degrader/__pycache__/BaseDegradation.cpython-37.pyc
audio_degrader/__pycache__/BaseDegradation.cpython-39.pyc
audio_degrader/__pycache__/DegradationConvolution.cpython-37.pyc
audio_degrader/__pycache__/DegradationConvolution.cpython-39.pyc
audio_degrader/__pycache__/DegradationDynamicRangeCompression.cpython-37.pyc
audio_degrader/__pycache__/DegradationEqualization.cpython-37.pyc
audio_degrader/__pycache__/DegradationGain.cpython-37.pyc
audio_degrader/__pycache__/DegradationMix.cpython-37.pyc
audio_degrader-1.3.1.dist-info/LICENSE.txt
audio_degrader-1.3.1.dist-info/METADATA
audio_degrader-1.3.1.dist-info/WHEEL
audio_degrader-1.3.1.dist-info/top_level.txt
audio_degrader-1.3.1.dist-info/RECORD
