Metadata-Version: 2.1
Name: audio-degrader
Version: 1.3.1
Summary: Tool to introduce controlled degradations to audio
Home-page: https://github.com/EliosMolina/audio_degrader
Author: Emilio Molina
Author-email: emilio.mol.mar@gmail.com
License: UNKNOWN
Download-URL: https://github.com/EliosMolina/audio_degrader/archive/master.zip
Keywords: audio,degradation,augmentation
Platform: UNKNOWN
Requires-Dist: SoundFile (==0.10.3.post1)
Requires-Dist: pytest (>=6.1.2)
Requires-Dist: scipy (>=1.4.1)
Requires-Dist: sox (==1.4.1)
